ansys/api/avxcelerate/VERSION
ansys/api/avxcelerate/__init__.py
ansys/api/avxcelerate/sensors/v1/colors.proto
ansys/api/avxcelerate/sensors/v1/colors_pb2.py
ansys/api/avxcelerate/sensors/v1/colors_pb2.pyi
ansys/api/avxcelerate/sensors/v1/colors_pb2_grpc.py
ansys/api/avxcelerate/sensors/v1/colors_pb2_grpc.pyi
ansys/api/avxcelerate/sensors/v1/geometry.proto
ansys/api/avxcelerate/sensors/v1/geometry_pb2.py
ansys/api/avxcelerate/sensors/v1/geometry_pb2.pyi
ansys/api/avxcelerate/sensors/v1/geometry_pb2_grpc.py
ansys/api/avxcelerate/sensors/v1/geometry_pb2_grpc.pyi
ansys/api/avxcelerate/sensors/v1/object_identifier.proto
ansys/api/avxcelerate/sensors/v1/object_identifier_pb2.py
ansys/api/avxcelerate/sensors/v1/object_identifier_pb2.pyi
ansys/api/avxcelerate/sensors/v1/object_identifier_pb2_grpc.py
ansys/api/avxcelerate/sensors/v1/object_identifier_pb2_grpc.pyi
ansys/api/avxcelerate/sensors/v1/resource_identifier.proto
ansys/api/avxcelerate/sensors/v1/resource_identifier_pb2.py
ansys/api/avxcelerate/sensors/v1/resource_identifier_pb2.pyi
ansys/api/avxcelerate/sensors/v1/resource_identifier_pb2_grpc.py
ansys/api/avxcelerate/sensors/v1/resource_identifier_pb2_grpc.pyi
ansys/api/avxcelerate/sensors/v1/sensor_data_format.proto
ansys/api/avxcelerate/sensors/v1/sensor_data_format_pb2.py
ansys/api/avxcelerate/sensors/v1/sensor_data_format_pb2.pyi
ansys/api/avxcelerate/sensors/v1/sensor_data_format_pb2_grpc.py
ansys/api/avxcelerate/sensors/v1/sensor_data_format_pb2_grpc.pyi
ansys/api/avxcelerate/sensors/v1/status.proto
ansys/api/avxcelerate/sensors/v1/status_pb2.py
ansys/api/avxcelerate/sensors/v1/status_pb2.pyi
ansys/api/avxcelerate/sensors/v1/status_pb2_grpc.py
ansys/api/avxcelerate/sensors/v1/status_pb2_grpc.pyi
ansys/api/avxcelerate/sensors/v1/tag_colors.proto
ansys/api/avxcelerate/sensors/v1/tag_colors_pb2.py
ansys/api/avxcelerate/sensors/v1/tag_colors_pb2.pyi
ansys/api/avxcelerate/sensors/v1/tag_colors_pb2_grpc.py
ansys/api/avxcelerate/sensors/v1/tag_colors_pb2_grpc.pyi
ansys_api_avxcelerate-0.2.0.dist-info/licenses/AUTHORS
ansys_api_avxcelerate-0.2.0.dist-info/licenses/LICENSE
ansys_api_avxcelerate-0.2.0.dist-info/METADATA
ansys_api_avxcelerate-0.2.0.dist-info/WHEEL
ansys_api_avxcelerate-0.2.0.dist-info/entry_points.txt
ansys_api_avxcelerate-0.2.0.dist-info/top_level.txt
ansys_api_avxcelerate-0.2.0.dist-info/RECORD
