Metadata-Version: 2.4
Name: ansys-api-avxcelerate
Version: 0.2.0
Summary: Autogenerated API package for ansys-api-avxcelerate, built on 15:56:59 on 05 November 2025
Home-page: https://github.com/ansys/ansys-api-avxcelerate
Author: ANSYS, Inc.
Author-email: pyansys.core@ansys.com
Maintainer: ANSYS, Inc.
Maintainer-email: pyansys.core@ansys.com
License: MIT
Requires-Python: >=3.10
License-File: LICENSE
License-File: AUTHORS
Requires-Dist: grpcio<2.0.0,>=1.50
Requires-Dist: protobuf<7,>=4.21.6
Dynamic: author
Dynamic: author-email
Dynamic: description
Dynamic: description-content-type
Dynamic: home-page
Dynamic: license
Dynamic: license-file
Dynamic: maintainer
Dynamic: maintainer-email
Dynamic: requires-dist
Dynamic: requires-python
Dynamic: summary
